{
    "title": {
        "en": "Around Dragons Teeth",
        "fi": "Lohik채채rmeiden hampaiden ymp채rill채",
        "fr": "Aux alentours des dents de dragon"
    },
    "description": {
        "en": "",
        "fi": "",
        "fr": ""
    },
    "story": "Around_Dragons_Teeth",
    "dateTaken": "2018-10-13T12:31:51",
    "focalLength35mm": 33,
    "exposureTime": "1/200",
    "fNumber": 5.0,
    "iso": 100,
    "prev": 181007091416,
    "next": 181013152552,
    "body": "NIKON D7100",
    "lens": "AF-S DX Nikkor 18-55mm f/3.5-5.6G VR II"
}
